LICENCE.md
README.md
setup.py
trackpad_configuration_manager/Bos1921Dataholder.py
trackpad_configuration_manager/__init__.py
trackpad_configuration_manager/cmsis_package.py
trackpad_configuration_manager/configuration.py
trackpad_configuration_manager/dataHolder.py
trackpad_configuration_manager/example.py
trackpad_configuration_manager/marshaller.py
trackpad_configuration_manager.egg-info/PKG-INFO
trackpad_configuration_manager.egg-info/SOURCES.txt
trackpad_configuration_manager.egg-info/dependency_links.txt
trackpad_configuration_manager.egg-info/not-zip-safe
trackpad_configuration_manager.egg-info/requires.txt
trackpad_configuration_manager.egg-info/top_level.txt
trackpad_configuration_manager/boreas_data_converter/bos1921DataConverter.py
trackpad_configuration_manager/probe/__init__.py
trackpad_configuration_manager/probe/probe.py
trackpad_configuration_manager/utils/__init__.py
trackpad_configuration_manager/utils/calibration_data_set.py
trackpad_configuration_manager/utils/crc16.py
trackpad_configuration_manager/utils/execUtils.py
trackpad_configuration_manager/utils/hexFile.py